hyperspec/__init__.py
hyperspec/__init__.pyi
hyperspec/_core.cpython-314t-x86_64-linux-gnu.so
hyperspec/_json_schema.py
hyperspec/_typing_utils.py
hyperspec/_typing_utils.pyi
hyperspec/_utils.py
hyperspec/_version.py
hyperspec/inspect.py
hyperspec/json.py
hyperspec/json.pyi
hyperspec/msgpack.py
hyperspec/msgpack.pyi
hyperspec/py.typed
hyperspec/structs.py
hyperspec/structs.pyi
hyperspec/toml.py
hyperspec/yaml.py
hyperlight_hyperspec-0.1.13.dist-info/METADATA
hyperlight_hyperspec-0.1.13.dist-info/WHEEL
hyperlight_hyperspec-0.1.13.dist-info/top_level.txt
hyperlight_hyperspec-0.1.13.dist-info/RECORD
hyperlight_hyperspec-0.1.13.dist-info/licenses/LICENSE
