Metadata-Version: 2.4
Name: hyperlight-hyperspec
Version: 0.1.13
Summary: A fast serialization and validation library, with builtin support for JSON, MessagePack, YAML, and TOML.
Maintainer-email: Jim Crist-Harif <jcristharif@gmail.com>, Ofek Lev <oss@ofek.dev>
License-Expression: BSD-3-Clause
Project-URL: Homepage, https://jcristharif.com/hyperspec/
Project-URL: Issue Tracker, https://github.com/jcrist/hyperspec/issues
Project-URL: Source, https://github.com/jcrist/hyperspec
Keywords: JSON,MessagePack,TOML,YAML,msgpack,schema,serialization,validation
Classifier: Development Status :: 4 - Beta
Classifier: Programming Language :: Python :: 3.10
Classifier: Programming Language :: Python :: 3.11
Classifier: Programming Language :: Python :: 3.12
Classifier: Programming Language :: Python :: 3.13
Classifier: Programming Language :: Python :: 3.14
Requires-Python: >=3.10
License-File: LICENSE
Provides-Extra: toml
Requires-Dist: tomli; python_version < "3.11" and extra == "toml"
Requires-Dist: tomli_w; extra == "toml"
Provides-Extra: yaml
Requires-Dist: pyyaml; extra == "yaml"
Dynamic: license-file
